{
  "step0_positional": {
    "f": {
      "initial": 118,
      "medial": 364,
      "final": 17,
      "standalone": 6,
      "total": 505
    },
    "i": {
      "initial": 15,
      "medial": 11711,
      "final": 6,
      "standalone": 0,
      "total": 11732
    },
    "q": {
      "initial": 5359,
      "medial": 63,
      "final": 0,
      "standalone": 1,
      "total": 5423
    }
  },
  "step0_qo_digram": {
    "initial": 5231,
    "medial": 56,
    "final": 4,
    "total": 5291,
    "q_before_o": 5291,
    "q_not_before_o": 132
  },
  "step0_strip_results": {
    "f": {
      "tested": 91,
      "hits": 40,
      "hit_rate": 44.0,
      "top_matches": [
        {
          "eva_word": "fchy",
          "stripped": "chy",
          "hebrew": "SEA",
          "italian": "sea",
          "match_lang": "italian",
          "match_word": "sea",
          "gloss": "scea (agg.)",
          "section": "herbal"
        },
        {
          "eva_word": "fary",
          "stripped": "ary",
          "hebrew": "Shy",
          "italian": "sei",
          "match_lang": "italian",
          "match_word": "sei",
          "gloss": "sei",
          "section": "text"
        },
        {
          "eva_word": "fodal",
          "stripped": "odal",
          "hebrew": "myrw",
          "italian": "miro",
          "match_lang": "italian",
          "match_word": "miro",
          "gloss": "miro (Dante, freq=3)",
          "section": "astronomical"
        },
        {
          "eva_word": "fchoy",
          "stripped": "choy",
          "hebrew": "SwEA",
          "italian": "soea",
          "match_lang": "italian~1",
          "match_word": "sea",
          "gloss": "scea (agg.)",
          "section": "herbal"
        },
        {
          "eva_word": "fchol",
          "stripped": "chol",
          "hebrew": "mwEA",
          "italian": "moea",
          "match_lang": "italian~1",
          "match_word": "mea",
          "gloss": "mea (Dante, freq=2)",
          "section": "herbal"
        },
        {
          "eva_word": "fchol",
          "stripped": "chol",
          "hebrew": "mwEA",
          "italian": "moea",
          "match_lang": "italian~1",
          "match_word": "mea",
          "gloss": "mea (Dante, freq=2)",
          "section": "herbal"
        },
        {
          "eva_word": "fchol",
          "stripped": "chol",
          "hebrew": "mwEA",
          "italian": "moea",
          "match_lang": "italian~1",
          "match_word": "mea",
          "gloss": "mea (Dante, freq=2)",
          "section": "herbal"
        },
        {
          "eva_word": "fcholy",
          "stripped": "choly",
          "hebrew": "SmwEA",
          "italian": "smoea",
          "match_lang": "italian~1",
          "match_word": "smosa",
          "gloss": "smossa (s.f.)",
          "section": "herbal"
        },
        {
          "eva_word": "fchom",
          "stripped": "chom",
          "hebrew": "gwEA",
          "italian": "goea",
          "match_lang": "italian~1",
          "match_word": "gona",
          "gloss": "gonna (s.f.)",
          "section": "herbal"
        },
        {
          "eva_word": "fsey",
          "stripped": "sey",
          "hebrew": "Spn",
          "italian": "spn",
          "match_lang": "hebrew",
          "match_word": "Spn",
          "gloss": "to treasure",
          "section": "herbal"
        }
      ]
    },
    "i": {
      "tested": 8,
      "hits": 4,
      "hit_rate": 50.0,
      "top_matches": [
        {
          "eva_word": "iphy",
          "stripped": "phy",
          "hebrew": "SEl",
          "italian": "sel",
          "match_lang": "italian",
          "match_word": "sel",
          "gloss": "scel (s.i.)",
          "section": "balneological"
        },
        {
          "eva_word": "ithey",
          "stripped": "they",
          "hebrew": "SpEJ",
          "italian": "spet",
          "match_lang": "italian~1",
          "match_word": "spei",
          "gloss": "spei (s.i.)",
          "section": "balneological"
        },
        {
          "eva_word": "ikhey",
          "stripped": "khey",
          "hebrew": "SpEt",
          "italian": "spet",
          "match_lang": "italian~1",
          "match_word": "spei",
          "gloss": "spei (s.i.)",
          "section": "balneological"
        },
        {
          "eva_word": "ithhy",
          "stripped": "thhy",
          "hebrew": "SEEJ",
          "italian": "seet",
          "match_lang": "italian~1",
          "match_word": "see",
          "gloss": "sei",
          "section": "balneological"
        }
      ]
    },
    "q": {
      "tested": 4062,
      "hits": 2462,
      "hit_rate": 60.6,
      "top_matches": [
        {
          "eva_word": "qoky",
          "stripped": "oky",
          "hebrew": "Stw",
          "italian": "sto",
          "match_lang": "italian",
          "match_word": "sto",
          "gloss": "sto (Dante, freq=2)",
          "section": "herbal"
        },
        {
          "eva_word": "qopal",
          "stripped": "opal",
          "hebrew": "mylw",
          "italian": "milo",
          "match_lang": "italian",
          "match_word": "milo",
          "gloss": "melo",
          "section": "herbal"
        },
        {
          "eva_word": "qokol",
          "stripped": "okol",
          "hebrew": "mwtw",
          "italian": "moto",
          "match_lang": "italian",
          "match_word": "moto",
          "gloss": "moto (s.m.)",
          "section": "herbal"
        },
        {
          "eva_word": "qokol",
          "stripped": "okol",
          "hebrew": "mwtw",
          "italian": "moto",
          "match_lang": "italian",
          "match_word": "moto",
          "gloss": "moto (s.m.)",
          "section": "herbal"
        },
        {
          "eva_word": "qopol",
          "stripped": "opol",
          "hebrew": "mwlw",
          "italian": "molo",
          "match_lang": "italian",
          "match_word": "molo",
          "gloss": "molo (s.m.)",
          "section": "herbal"
        },
        {
          "eva_word": "qotoy",
          "stripped": "otoy",
          "hebrew": "SwJw",
          "italian": "soto",
          "match_lang": "italian",
          "match_word": "soto",
          "gloss": "sotto",
          "section": "herbal"
        },
        {
          "eva_word": "qoty",
          "stripped": "oty",
          "hebrew": "SJw",
          "italian": "sto",
          "match_lang": "italian",
          "match_word": "sto",
          "gloss": "sto (Dante, freq=2)",
          "section": "herbal"
        },
        {
          "eva_word": "qokshy",
          "stripped": "okshy",
          "hebrew": "SEntw",
          "italian": "sento",
          "match_lang": "italian",
          "match_word": "sento",
          "gloss": "sento (Dante, freq=4)",
          "section": "herbal"
        },
        {
          "eva_word": "qotol",
          "stripped": "otol",
          "hebrew": "mwJw",
          "italian": "moto",
          "match_lang": "italian",
          "match_word": "moto",
          "gloss": "moto (s.m.)",
          "section": "herbal"
        },
        {
          "eva_word": "qokoy",
          "stripped": "okoy",
          "hebrew": "Swtw",
          "italian": "soto",
          "match_lang": "italian",
          "match_word": "soto",
          "gloss": "sotto",
          "section": "herbal"
        }
      ]
    },
    "qo": {
      "tested": 3647,
      "hits": 895,
      "hit_rate": 24.5,
      "top_matches": [
        {
          "eva_word": "qotoy",
          "stripped": "toy",
          "hebrew": "SwJ",
          "italian": "sot",
          "match_lang": "italian",
          "match_word": "sot",
          "gloss": "sott (Dante, freq=5)",
          "section": "herbal"
        },
        {
          "eva_word": "qocthy",
          "stripped": "cthy",
          "hebrew": "SEJA",
          "italian": "seta",
          "match_lang": "italian",
          "match_word": "seta",
          "gloss": "setta (s.f.)",
          "section": "herbal"
        },
        {
          "eva_word": "qooko",
          "stripped": "oko",
          "hebrew": "wtw",
          "italian": "oto",
          "match_lang": "italian",
          "match_word": "oto",
          "gloss": "otto",
          "section": "herbal"
        },
        {
          "eva_word": "qokoy",
          "stripped": "koy",
          "hebrew": "Swt",
          "italian": "sot",
          "match_lang": "italian",
          "match_word": "sot",
          "gloss": "sott (Dante, freq=5)",
          "section": "herbal"
        },
        {
          "eva_word": "qokam",
          "stripped": "kam",
          "hebrew": "gyt",
          "italian": "git",
          "match_lang": "italian",
          "match_word": "git",
          "gloss": "git (s.m.)",
          "section": "herbal"
        },
        {
          "eva_word": "qocky",
          "stripped": "cky",
          "hebrew": "StA",
          "italian": "sta",
          "match_lang": "italian",
          "match_word": "sta",
          "gloss": "sta (s.f.)",
          "section": "herbal"
        },
        {
          "eva_word": "qocthy",
          "stripped": "cthy",
          "hebrew": "SEJA",
          "italian": "seta",
          "match_lang": "italian",
          "match_word": "seta",
          "gloss": "setta (s.f.)",
          "section": "herbal"
        },
        {
          "eva_word": "qodam",
          "stripped": "dam",
          "hebrew": "gyr",
          "italian": "gir",
          "match_lang": "italian",
          "match_word": "gir",
          "gloss": "gir (Dante, freq=6)",
          "section": "herbal"
        },
        {
          "eva_word": "qokam",
          "stripped": "kam",
          "hebrew": "gyt",
          "italian": "git",
          "match_lang": "italian",
          "match_word": "git",
          "gloss": "git (s.m.)",
          "section": "herbal"
        },
        {
          "eva_word": "qochy",
          "stripped": "chy",
          "hebrew": "SEA",
          "italian": "sea",
          "match_lang": "italian",
          "match_word": "sea",
          "gloss": "scea (agg.)",
          "section": "herbal"
        }
      ]
    }
  },
  "step0_prefix_ids": {
    "f": {
      "prefix": null,
      "confidence": "none",
      "reason": "initial=23%, hit_rate=44.0% — not consistent with prefix hypothesis",
      "initial_pct": 23.4,
      "strip_hit_rate": 44.0
    },
    "i": {
      "prefix": null,
      "confidence": "none",
      "reason": "initial=0%, hit_rate=50.0% — not consistent with prefix hypothesis",
      "initial_pct": 0.1,
      "strip_hit_rate": 50.0
    },
    "q": {
      "prefix": "w",
      "prefix_name": "vav",
      "prefix_form": "ve-",
      "meaning": "and",
      "confidence": "high",
      "reason": "initial=99%, strip_hit_rate=60.6%, corpus_freq=0.146",
      "initial_pct": 98.8,
      "strip_hit_rate": 60.6
    }
  },
  "step1_counts": {
    "type_a": 1541,
    "type_b": 115,
    "type_c": 844,
    "type_a_by_char": {
      "q": 683,
      "i": 594,
      "f": 252,
      "z": 1,
      "x": 11
    }
  },
  "step2_brute_force": {
    "f": {
      "n_words": 283,
      "top5": [
        {
          "hebrew_letter": "S",
          "hebrew_name": "shin",
          "italian_phoneme": "s",
          "total_hits": 60,
          "exact_hits": 10,
          "hits_5plus": 3,
          "misses": 223,
          "total_tested": 283,
          "hit_rate": 21.2,
          "already_mapped": true
        },
        {
          "hebrew_letter": "r",
          "hebrew_name": "resh",
          "italian_phoneme": "r",
          "total_hits": 62,
          "exact_hits": 8,
          "hits_5plus": 3,
          "misses": 221,
          "total_tested": 283,
          "hit_rate": 21.9,
          "already_mapped": true
        },
        {
          "hebrew_letter": "s",
          "hebrew_name": "samekh",
          "italian_phoneme": "s",
          "total_hits": 59,
          "exact_hits": 8,
          "hits_5plus": 3,
          "misses": 224,
          "total_tested": 283,
          "hit_rate": 20.8,
          "already_mapped": false
        },
        {
          "hebrew_letter": "t",
          "hebrew_name": "tav",
          "italian_phoneme": "t",
          "total_hits": 58,
          "exact_hits": 6,
          "hits_5plus": 3,
          "misses": 225,
          "total_tested": 283,
          "hit_rate": 20.5,
          "already_mapped": true
        },
        {
          "hebrew_letter": "J",
          "hebrew_name": "tet",
          "italian_phoneme": "t",
          "total_hits": 57,
          "exact_hits": 5,
          "hits_5plus": 3,
          "misses": 226,
          "total_tested": 283,
          "hit_rate": 20.1,
          "already_mapped": true
        }
      ]
    },
    "i": {
      "n_words": 637,
      "top5": [
        {
          "hebrew_letter": "d",
          "hebrew_name": "dalet",
          "italian_phoneme": "d",
          "total_hits": 210,
          "exact_hits": 20,
          "hits_5plus": 14,
          "misses": 427,
          "total_tested": 637,
          "hit_rate": 33.0,
          "already_mapped": true
        },
        {
          "hebrew_letter": "r",
          "hebrew_name": "resh",
          "italian_phoneme": "r",
          "total_hits": 177,
          "exact_hits": 14,
          "hits_5plus": 8,
          "misses": 460,
          "total_tested": 637,
          "hit_rate": 27.8,
          "already_mapped": true
        },
        {
          "hebrew_letter": "g",
          "hebrew_name": "gimel",
          "italian_phoneme": "g",
          "total_hits": 103,
          "exact_hits": 11,
          "hits_5plus": 5,
          "misses": 534,
          "total_tested": 637,
          "hit_rate": 16.2,
          "already_mapped": true
        },
        {
          "hebrew_letter": "J",
          "hebrew_name": "tet",
          "italian_phoneme": "t",
          "total_hits": 135,
          "exact_hits": 8,
          "hits_5plus": 5,
          "misses": 502,
          "total_tested": 637,
          "hit_rate": 21.2,
          "already_mapped": true
        },
        {
          "hebrew_letter": "t",
          "hebrew_name": "tav",
          "italian_phoneme": "t",
          "total_hits": 134,
          "exact_hits": 8,
          "hits_5plus": 5,
          "misses": 503,
          "total_tested": 637,
          "hit_rate": 21.0,
          "already_mapped": true
        }
      ]
    },
    "q": {
      "n_words": 719,
      "top5": [
        {
          "hebrew_letter": "r",
          "hebrew_name": "resh",
          "italian_phoneme": "r",
          "total_hits": 137,
          "exact_hits": 6,
          "hits_5plus": 3,
          "misses": 582,
          "total_tested": 719,
          "hit_rate": 19.1,
          "already_mapped": true
        },
        {
          "hebrew_letter": "X",
          "hebrew_name": "chet",
          "italian_phoneme": "k",
          "total_hits": 79,
          "exact_hits": 6,
          "hits_5plus": 3,
          "misses": 640,
          "total_tested": 719,
          "hit_rate": 11.0,
          "already_mapped": true
        },
        {
          "hebrew_letter": "w",
          "hebrew_name": "vav",
          "italian_phoneme": "o",
          "total_hits": 105,
          "exact_hits": 8,
          "hits_5plus": 2,
          "misses": 614,
          "total_tested": 719,
          "hit_rate": 14.6,
          "already_mapped": true
        },
        {
          "hebrew_letter": "A",
          "hebrew_name": "aleph",
          "italian_phoneme": "a",
          "total_hits": 109,
          "exact_hits": 6,
          "hits_5plus": 2,
          "misses": 610,
          "total_tested": 719,
          "hit_rate": 15.2,
          "already_mapped": true
        },
        {
          "hebrew_letter": "s",
          "hebrew_name": "samekh",
          "italian_phoneme": "s",
          "total_hits": 106,
          "exact_hits": 3,
          "hits_5plus": 2,
          "misses": 613,
          "total_tested": 719,
          "hit_rate": 14.7,
          "already_mapped": false
        }
      ]
    },
    "x": {
      "n_words": 16,
      "top5": [
        {
          "hebrew_letter": "l",
          "hebrew_name": "lamed",
          "italian_phoneme": "l",
          "total_hits": 7,
          "exact_hits": 1,
          "hits_5plus": 0,
          "misses": 9,
          "total_tested": 16,
          "hit_rate": 43.8,
          "already_mapped": true
        },
        {
          "hebrew_letter": "h",
          "hebrew_name": "he",
          "italian_phoneme": "e",
          "total_hits": 6,
          "exact_hits": 1,
          "hits_5plus": 0,
          "misses": 10,
          "total_tested": 16,
          "hit_rate": 37.5,
          "already_mapped": true
        },
        {
          "hebrew_letter": "m",
          "hebrew_name": "mem",
          "italian_phoneme": "m",
          "total_hits": 6,
          "exact_hits": 1,
          "hits_5plus": 0,
          "misses": 10,
          "total_tested": 16,
          "hit_rate": 37.5,
          "already_mapped": true
        },
        {
          "hebrew_letter": "n",
          "hebrew_name": "nun",
          "italian_phoneme": "n",
          "total_hits": 7,
          "exact_hits": 0,
          "hits_5plus": 0,
          "misses": 9,
          "total_tested": 16,
          "hit_rate": 43.8,
          "already_mapped": true
        },
        {
          "hebrew_letter": "r",
          "hebrew_name": "resh",
          "italian_phoneme": "r",
          "total_hits": 7,
          "exact_hits": 0,
          "hits_5plus": 0,
          "misses": 9,
          "total_tested": 16,
          "hit_rate": 43.8,
          "already_mapped": true
        }
      ]
    },
    "z": {
      "n_words": 1,
      "top5": [
        {
          "hebrew_letter": "A",
          "hebrew_name": "aleph",
          "italian_phoneme": "a",
          "total_hits": 0,
          "exact_hits": 0,
          "hits_5plus": 0,
          "misses": 1,
          "total_tested": 1,
          "hit_rate": 0.0,
          "already_mapped": true
        },
        {
          "hebrew_letter": "b",
          "hebrew_name": "bet",
          "italian_phoneme": "b",
          "total_hits": 0,
          "exact_hits": 0,
          "hits_5plus": 0,
          "misses": 1,
          "total_tested": 1,
          "hit_rate": 0.0,
          "already_mapped": false
        },
        {
          "hebrew_letter": "g",
          "hebrew_name": "gimel",
          "italian_phoneme": "g",
          "total_hits": 0,
          "exact_hits": 0,
          "hits_5plus": 0,
          "misses": 1,
          "total_tested": 1,
          "hit_rate": 0.0,
          "already_mapped": true
        },
        {
          "hebrew_letter": "d",
          "hebrew_name": "dalet",
          "italian_phoneme": "d",
          "total_hits": 0,
          "exact_hits": 0,
          "hits_5plus": 0,
          "misses": 1,
          "total_tested": 1,
          "hit_rate": 0.0,
          "already_mapped": true
        },
        {
          "hebrew_letter": "h",
          "hebrew_name": "he",
          "italian_phoneme": "e",
          "total_hits": 0,
          "exact_hits": 0,
          "hits_5plus": 0,
          "misses": 1,
          "total_tested": 1,
          "hit_rate": 0.0,
          "already_mapped": true
        }
      ]
    }
  },
  "step3_decisions": {
    "f": {
      "best": "s",
      "best_name": "samekh",
      "best_italian": "s",
      "total_hits": 59,
      "exact_hits": 8,
      "hits_5plus": 3,
      "hit_rate": 20.8,
      "margin": 1.74,
      "second_best": "z",
      "second_hits": 34,
      "confidence": "medium",
      "n_sections": 5,
      "sections": [
        "A",
        "balneological",
        "cosmological",
        "herbal",
        "text"
      ],
      "conflicts_with": null,
      "top_examples": [
        {
          "eva_word": "cfhol",
          "hebrew": "mwEsA",
          "italian": "moesa",
          "count": 6,
          "section": "text",
          "lang": "italian",
          "match": "morsa",
          "distance": 1,
          "gloss": "morsa (s.f.)"
        },
        {
          "eva_word": "cfhy",
          "hebrew": "SEsA",
          "italian": "sesa",
          "count": 6,
          "section": "herbal",
          "lang": "italian",
          "match": "sesa",
          "distance": 0,
          "gloss": "scesa (s.f.)"
        },
        {
          "eva_word": "ofchey",
          "hebrew": "SpEAsw",
          "italian": "speaso",
          "count": 4,
          "section": "herbal",
          "lang": "italian",
          "match": "speso",
          "distance": 1,
          "gloss": "speso (s.m.)"
        },
        {
          "eva_word": "ofar",
          "hebrew": "hysw",
          "italian": "eiso",
          "count": 4,
          "section": "herbal",
          "lang": "italian",
          "match": "siso",
          "distance": 1,
          "gloss": "scisso (agg.)"
        },
        {
          "eva_word": "ofchy",
          "hebrew": "SEAsw",
          "italian": "seaso",
          "count": 3,
          "section": "herbal",
          "lang": "italian",
          "match": "suaso",
          "distance": 1,
          "gloss": "suaso (agg.)"
        }
      ]
    },
    "i": {
      "best": "s",
      "best_name": "samekh",
      "best_italian": "s",
      "total_hits": 117,
      "exact_hits": 5,
      "hits_5plus": 4,
      "hit_rate": 18.4,
      "margin": "inf",
      "second_best": null,
      "second_hits": 0,
      "confidence": "high",
      "n_sections": 3,
      "sections": [
        "A",
        "herbal",
        "text"
      ],
      "conflicts_with": null,
      "top_examples": [
        {
          "eva_word": "dain",
          "hebrew": "dsyr",
          "italian": "dsir",
          "count": 189,
          "section": "text",
          "lang": "italian",
          "match": "disir",
          "distance": 1,
          "gloss": "disir (Dante, freq=3)"
        },
        {
          "eva_word": "okain",
          "hebrew": "dsytw",
          "italian": "dsito",
          "count": 141,
          "section": "text",
          "lang": "italian",
          "match": "sito",
          "distance": 1,
          "gloss": "sito (Dante, freq=7)"
        },
        {
          "eva_word": "dair",
          "hebrew": "hsyr",
          "italian": "esir",
          "count": 100,
          "section": "text",
          "lang": "italian",
          "match": "esia",
          "distance": 1,
          "gloss": "essia (cong.)"
        },
        {
          "eva_word": "otain",
          "hebrew": "dsyJw",
          "italian": "dsito",
          "count": 95,
          "section": "herbal",
          "lang": "italian",
          "match": "sito",
          "distance": 1,
          "gloss": "sito (Dante, freq=7)"
        },
        {
          "eva_word": "sair",
          "hebrew": "hsyn",
          "italian": "esin",
          "count": 27,
          "section": "herbal",
          "lang": "italian",
          "match": "esia",
          "distance": 1,
          "gloss": "essia (cong.)"
        }
      ]
    },
    "q": {
      "best": "s",
      "best_name": "samekh",
      "best_italian": "s",
      "total_hits": 106,
      "exact_hits": 3,
      "hits_5plus": 2,
      "hit_rate": 14.7,
      "margin": "inf",
      "second_best": null,
      "second_hits": 0,
      "confidence": "medium",
      "n_sections": 1,
      "sections": [
        "herbal"
      ],
      "conflicts_with": null,
      "top_examples": [
        {
          "eva_word": "qokeey",
          "hebrew": "Spptws",
          "italian": "spptos",
          "count": 308,
          "section": "herbal",
          "lang": "italian",
          "match": "sotos",
          "distance": 1,
          "gloss": "sotos (s.m.)"
        },
        {
          "eva_word": "qokal",
          "hebrew": "mytws",
          "italian": "mitos",
          "count": 188,
          "section": "herbal",
          "lang": "italian",
          "match": "minos",
          "distance": 1,
          "gloss": "minos (Dante, freq=7)"
        },
        {
          "eva_word": "qoky",
          "hebrew": "Stws",
          "italian": "stos",
          "count": 139,
          "section": "herbal",
          "lang": "italian",
          "match": "sto",
          "distance": 1,
          "gloss": "sto (Dante, freq=2)"
        },
        {
          "eva_word": "qokey",
          "hebrew": "Sptws",
          "italian": "sptos",
          "count": 105,
          "section": "herbal",
          "lang": "italian",
          "match": "sotos",
          "distance": 1,
          "gloss": "sotos (s.m.)"
        },
        {
          "eva_word": "qokol",
          "hebrew": "mwtws",
          "italian": "motos",
          "count": 102,
          "section": "herbal",
          "lang": "italian",
          "match": "motor",
          "distance": 1,
          "gloss": "motor (Dante, freq=3)"
        }
      ]
    },
    "x": {
      "best": "s",
      "best_name": "samekh",
      "best_italian": "s",
      "total_hits": 5,
      "exact_hits": 0,
      "hits_5plus": 0,
      "hit_rate": 31.2,
      "margin": 1.0,
      "second_best": "C",
      "second_hits": 5,
      "confidence": "low",
      "n_sections": 2,
      "sections": [
        "astronomical",
        "text"
      ],
      "conflicts_with": null,
      "top_examples": [
        {
          "eva_word": "cholxy",
          "hebrew": "SsmwEA",
          "italian": "ssmoea",
          "count": 1,
          "section": "astronomical",
          "lang": "italian",
          "match": "smosa",
          "distance": 1,
          "gloss": "smossa (s.f.)"
        },
        {
          "eva_word": "oshox",
          "hebrew": "swEnw",
          "italian": "soeno",
          "count": 1,
          "section": "astronomical",
          "lang": "italian",
          "match": "seno",
          "distance": 1,
          "gloss": "senno (avv./cong.)"
        },
        {
          "eva_word": "axor",
          "hebrew": "hwsy",
          "italian": "eosi",
          "count": 1,
          "section": "text",
          "lang": "italian",
          "match": "mosi",
          "distance": 1,
          "gloss": "mosi (s.m.)"
        },
        {
          "eva_word": "oxor",
          "hebrew": "hwsw",
          "italian": "eoso",
          "count": 1,
          "section": "astronomical",
          "lang": "italian",
          "match": "boso",
          "distance": 1,
          "gloss": "bosso (s.m.)"
        },
        {
          "eva_word": "oxar",
          "hebrew": "hysw",
          "italian": "eiso",
          "count": 1,
          "section": "astronomical",
          "lang": "italian",
          "match": "siso",
          "distance": 1,
          "gloss": "scisso (agg.)"
        }
      ]
    },
    "z": {
      "best": "b",
      "best_name": "bet",
      "best_italian": "b",
      "total_hits": 0,
      "exact_hits": 0,
      "hits_5plus": 0,
      "hit_rate": 0.0,
      "margin": 0,
      "second_best": "z",
      "second_hits": 0,
      "confidence": "none",
      "n_sections": 0,
      "sections": [],
      "conflicts_with": null,
      "top_examples": []
    }
  },
  "step4_validation": {
    "base_matches": 45,
    "base_occurrences": 664,
    "extended_matches": 49,
    "extended_occurrences": 723,
    "delta_matches": 4,
    "delta_occurrences": 59,
    "new_exact_matches": [],
    "new_chars_tested": {
      "f": "s",
      "i": "s",
      "q": "s"
    }
  },
  "step5_cascade": {
    "total_resolved": 841,
    "with_match": 8,
    "top20": [
      {
        "eva_word": "aiir",
        "hebrew": "hssy",
        "italian": "essi",
        "count": 23,
        "match": {
          "lang": "italian",
          "match": "esi",
          "gloss": "essi (Dante, freq=14)"
        }
      },
      {
        "eva_word": "okaiir",
        "hebrew": "hssytw",
        "italian": "essito",
        "count": 6,
        "match": {
          "lang": "italian",
          "match": "esito",
          "gloss": "escito (s.m.)"
        }
      },
      {
        "eva_word": "otaiir",
        "hebrew": "hssyJw",
        "italian": "essito",
        "count": 4,
        "match": {
          "lang": "italian",
          "match": "esito",
          "gloss": "escito (s.m.)"
        }
      },
      {
        "eva_word": "oiir",
        "hebrew": "hssw",
        "italian": "esso",
        "count": 3,
        "match": {
          "lang": "italian",
          "match": "eso",
          "gloss": "esso (avv.)"
        }
      },
      {
        "eva_word": "qof",
        "hebrew": "sws",
        "italian": "sos",
        "count": 1,
        "match": {
          "lang": "hebrew",
          "match": "sws",
          "gloss": "swallow, swift"
        }
      },
      {
        "eva_word": "aiil",
        "hebrew": "mssy",
        "italian": "mssi",
        "count": 1,
        "match": {
          "lang": "italian",
          "match": "msi",
          "gloss": "msi (name, historical)"
        }
      },
      {
        "eva_word": "otiir",
        "hebrew": "hssJw",
        "italian": "essto",
        "count": 1,
        "match": {
          "lang": "italian",
          "match": "esto",
          "gloss": "esto (avv.)"
        }
      },
      {
        "eva_word": "raify",
        "hebrew": "Sssyh",
        "italian": "sssie",
        "count": 1,
        "match": {
          "lang": "italian",
          "match": "sie",
          "gloss": "sie (Dante, freq=12)"
        }
      }
    ]
  },
  "final_mapping": {
    "a": {
      "hebrew": "y",
      "name": "yod",
      "italian": "i",
      "confidence": "convergent"
    },
    "c": {
      "hebrew": "A",
      "name": "aleph",
      "italian": "a",
      "confidence": "convergent"
    },
    "d": {
      "hebrew": "r",
      "name": "resh",
      "italian": "r",
      "confidence": "convergent"
    },
    "e": {
      "hebrew": "p",
      "name": "pe",
      "italian": "p",
      "confidence": "convergent"
    },
    "f": {
      "hebrew": "s",
      "name": "samekh",
      "italian": "s",
      "confidence": "medium"
    },
    "g": {
      "hebrew": "X",
      "name": "chet",
      "italian": "k",
      "confidence": "convergent"
    },
    "h": {
      "hebrew": "E",
      "name": "ayin",
      "italian": "e",
      "confidence": "convergent"
    },
    "i": {
      "hebrew": "s",
      "name": "samekh",
      "italian": "s",
      "confidence": "high"
    },
    "k": {
      "hebrew": "t",
      "name": "tav",
      "italian": "t",
      "confidence": "convergent"
    },
    "l": {
      "hebrew": "m",
      "name": "mem",
      "italian": "m",
      "confidence": "convergent"
    },
    "m": {
      "hebrew": "g",
      "name": "gimel",
      "italian": "g",
      "confidence": "convergent"
    },
    "n": {
      "hebrew": "d",
      "name": "dalet",
      "italian": "d",
      "confidence": "convergent"
    },
    "o": {
      "hebrew": "w",
      "name": "vav",
      "italian": "o",
      "confidence": "convergent"
    },
    "p": {
      "hebrew": "l",
      "name": "lamed",
      "italian": "l",
      "confidence": "convergent"
    },
    "q": {
      "hebrew": "s",
      "name": "samekh",
      "italian": "s",
      "confidence": "medium"
    },
    "r": {
      "hebrew": "h",
      "name": "he",
      "italian": "e",
      "confidence": "convergent"
    },
    "s": {
      "hebrew": "n",
      "name": "nun",
      "italian": "n",
      "confidence": "convergent"
    },
    "t": {
      "hebrew": "J",
      "name": "tet",
      "italian": "t",
      "confidence": "convergent"
    },
    "y": {
      "hebrew": "S",
      "name": "shin",
      "italian": "s",
      "confidence": "convergent"
    }
  },
  "verdict": {
    "high_confidence": [
      "i"
    ],
    "medium_confidence": [
      "q",
      "f"
    ],
    "low_confidence": [],
    "unresolved": [],
    "delta_anchors": 4
  }
}